docs/tutorial/train_racing_agent.py
tactics2d/__init__.py
tactics2d/dataset_parser/__init__.py
tactics2d/dataset_parser/map.config
tactics2d/dataset_parser/parse_argoverse.py
tactics2d/dataset_parser/parse_dlp.py
tactics2d/dataset_parser/parse_interaction.py
tactics2d/dataset_parser/parse_levelx.py
tactics2d/dataset_parser/parse_ngsim.py
tactics2d/dataset_parser/parse_nuplan.py
tactics2d/dataset_parser/parse_womd.py
tactics2d/dataset_parser/womd_proto/__init__.py
tactics2d/dataset_parser/womd_proto/pb2/__init__.py
tactics2d/dataset_parser/womd_proto/pb2/compressed_lidar_pb2.py
tactics2d/dataset_parser/womd_proto/pb2/dataset_pb2.py
tactics2d/dataset_parser/womd_proto/pb2/keypoint_pb2.py
tactics2d/dataset_parser/womd_proto/pb2/label_pb2.py
tactics2d/dataset_parser/womd_proto/pb2/map_pb2.py
tactics2d/dataset_parser/womd_proto/pb2/scenario_pb2.py
tactics2d/dataset_parser/womd_proto/pb2/vector_pb2.py
tactics2d/dataset_parser/womd_proto/pb3/__init__.py
tactics2d/dataset_parser/womd_proto/pb3/compressed_lidar_pb2.py
tactics2d/dataset_parser/womd_proto/pb3/dataset_pb2.py
tactics2d/dataset_parser/womd_proto/pb3/keypoint_pb2.py
tactics2d/dataset_parser/womd_proto/pb3/label_pb2.py
tactics2d/dataset_parser/womd_proto/pb3/map_pb2.py
tactics2d/dataset_parser/womd_proto/pb3/scenario_pb2.py
tactics2d/dataset_parser/womd_proto/pb3/vector_pb2.py
tactics2d/envs/__init__.py
tactics2d/envs/parking.py
tactics2d/envs/racing.py
tactics2d/envs/urban.py
tactics2d/map/__init__.py
tactics2d/map/converter/__init__.py
tactics2d/map/converter/gpkg2osm.py
tactics2d/map/converter/xodr2osm.py
tactics2d/map/element/__init__.py
tactics2d/map/element/area.py
tactics2d/map/element/junction.py
tactics2d/map/element/lane.py
tactics2d/map/element/map.py
tactics2d/map/element/node.py
tactics2d/map/element/regulatory.py
tactics2d/map/element/roadline.py
tactics2d/map/generator/__init__.py
tactics2d/map/generator/generate_parking_lot.py
tactics2d/map/generator/generate_racing_track.py
tactics2d-0.1.7.dist-info/LICENSE
tactics2d-0.1.7.dist-info/METADATA
tactics2d-0.1.7.dist-info/WHEEL
tactics2d-0.1.7.dist-info/top_level.txt
tactics2d-0.1.7.dist-info/RECORD
