Metadata-Version: 2.1
Name: tactics2d
Version: 0.1.7
Summary: Tactics2D: A Reinforcement Learning Environment Library with Generative Scenarios for Driving Decision-making
Author-email: Yueyuan Li <rowena.academic@gmail.com>
Maintainer-email: Yueyuan Li <rowena.academic@gmail.com>
License: GNU GENERAL PUBLIC LICENSE
Project-URL: Documentation, https://tactics2d.readthedocs.io/en/latest/
Project-URL: Repository, https://github.com/WoodOxen/tactics2d
Keywords: reinforcement-learning,environment,simulator,decision-making,traffic-behavior
Classifier: Development Status :: 4 - Beta
Classifier: License :: OSI Approved :: GNU General Public License v3 (GPLv3)
Classifier: Programming Language :: Python :: 3
Classifier: Operating System :: POSIX :: Linux
Classifier: Operating System :: MacOS
Classifier: Operating System :: Microsoft :: Windows
Requires-Python: >=3.8
License-File: LICENSE
Requires-Dist: fastparquet >=2022.11.0
Requires-Dist: geopandas >=0.10.2
Requires-Dist: gymnasium >=0.28.0
Requires-Dist: joblib >=1.3.2
Requires-Dist: matplotlib <3.8.0,>=3.7.0
Requires-Dist: numpy >=1.21.5
Requires-Dist: pandas >=1.5.3
Requires-Dist: protobuf <=3.20.3
Requires-Dist: pygame >=2.5.2
Requires-Dist: pyogrio ==0.7.2
Requires-Dist: pyproj >=3.2.1
Requires-Dist: scikit-learn >=1.0.0
Requires-Dist: scipy >=1.7.3
Requires-Dist: shapely >=2.0.2
Requires-Dist: tabulate >=0.9.0
Requires-Dist: tensorflow >=2.11.0
Provides-Extra: test
Requires-Dist: bezier ; extra == 'test'
Requires-Dist: Pillow ; extra == 'test'
Requires-Dist: pytest ; extra == 'test'
Requires-Dist: pytest-cov ; extra == 'test'
